Metadata-Version: 2.4
Name: strictly_typed_pandas
Version: 0.3.6
Summary: Static type checking of pandas DataFrames
Home-page: https://github.com/nanne-aben/strictly_typed_pandas
Author: Nanne Aben
Author-email: nanne.aben@gmail.com
License: MIT
Keywords: typing type checking pandas mypy linting
Classifier: Typing :: Typed
Requires-Python: >=3.8.0
License-File: LICENSE
Requires-Dist: numpy<=2.2.4
Requires-Dist: pandas<=2.2.3
Requires-Dist: pandas-stubs<=2.2.3.250308
Dynamic: author
Dynamic: author-email
Dynamic: classifier
Dynamic: description
Dynamic: description-content-type
Dynamic: home-page
Dynamic: keywords
Dynamic: license
Dynamic: license-file
Dynamic: requires-dist
Dynamic: requires-python
Dynamic: summary
